hrcl_jobs/__init__.py
hrcl_jobs/data.py
hrcl_jobs/dataset.py
hrcl_jobs/examples.py
hrcl_jobs/jobspec.py
hrcl_jobs/parallel.py
hrcl_jobs/pgsql.py
hrcl_jobs/s22.py
hrcl_jobs/serial.py
hrcl_jobs/setup.py
hrcl_jobs/sqlt.py
hrcl_jobs/tools_og.py
hrcl_jobs/utils.py
hrcl_jobs_docking/__init__.py
hrcl_jobs_docking/datasets.py
hrcl_jobs_docking/docking_inps.py
hrcl_jobs_docking/jobspec.py
hrcl_jobs_orca/__init__.py
hrcl_jobs_orca/jobspec.py
hrcl_jobs_orca/orca_inps.py
hrcl_jobs_psi4/__init__.py
hrcl_jobs_psi4/basis_sets.py
hrcl_jobs_psi4/datasets.py
hrcl_jobs_psi4/jobspec.py
hrcl_jobs_psi4/methods.py
hrcl_jobs_psi4/psi4_inps.py
hrcl_jobs_qcfractal/__init__.py
hrcl_jobs_qcfractal/jobspec.py
hrcl_jobs_qcfractal/psi4_inps.py
hrcl_jobs_qcfractal/serial.py
hrcl_jobs-1.8.1.dist-info/LICENSE
hrcl_jobs-1.8.1.dist-info/METADATA
hrcl_jobs-1.8.1.dist-info/WHEEL
hrcl_jobs-1.8.1.dist-info/top_level.txt
hrcl_jobs-1.8.1.dist-info/zip-safe
hrcl_jobs-1.8.1.dist-info/RECORD
