Metadata-Version: 2.1
Name: hrcl_jobs
Version: 1.8.1
Summary: Runs python functions on worker threads with main thread communicating with sql/postgresql db
Author-email: "Austin M. Wallace" <awallace43@gatech.edu>
Project-URL: Homepage, https://github.com/Awallace3/hierarchical_python_jobs
Project-URL: Bug Tracker, https://github.com/Awallace3/hierarchical_python_jobs/issues
Classifier: Programming Language :: Python :: 3
Classifier: License :: OSI Approved :: MIT License
Classifier: Operating System :: OS Independent
Requires-Python: >=3.8
License-File: LICENSE
Requires-Dist: matplotlib
Requires-Dist: qm-tools-aw
Requires-Dist: numpy >=1.20.0
Requires-Dist: pandas >=1.4.3
Provides-Extra: ad4_vina_calculations
Requires-Dist: autodock-vina ; extra == 'ad4_vina_calculations'
Provides-Extra: openmm_calculations
Requires-Dist: openmm ; extra == 'openmm_calculations'
Provides-Extra: psi4_calculations
Requires-Dist: psi4 >=1.7 ; extra == 'psi4_calculations'
